condor/__init__.py
condor/_version.py
condor/conf.py
condor/contrib.py
condor/fields.py
condor/models.py
condor/backend/__init__.py
condor/backend/_get_backend.py
condor/backend/operators.py
condor/backends/default.py
condor/backends/element_mixin.py
condor/backends/casadi/__init__.py
condor/backends/casadi/operators.py
condor/implementations/__init__.py
condor/implementations/iterative.py
condor/implementations/sgm_trajectory.py
condor/implementations/simple.py
condor/implementations/utils.py
condor/solvers/__init__.py
condor/solvers/casadi_warmstart_wrapper.py
condor/solvers/newton.py
condor/solvers/sweeping_gradient_method.py
condor-0.3.2.dist-info/licenses/LICENSE
condor-0.3.2.dist-info/METADATA
condor-0.3.2.dist-info/WHEEL
condor-0.3.2.dist-info/top_level.txt
condor-0.3.2.dist-info/RECORD
