Metadata-Version: 2.4
Name: condor
Version: 0.3.2
Summary: A package for disciplined systems modeling on a deadline
Author-email: "Benjamin W. L. Margolis" <benjamin.margolis@nasa.gov>, "Kenneth R. Lyons" <kenneth.r.lyons@nasa.gov>
License-Expression: NASA-1.3
Project-URL: Repository, https://github.com/nasa/condor
Project-URL: Documentation, https://nasa.github.io/condor
Project-URL: Issues, https://github.com/nasa/condor/issues
Classifier: Programming Language :: Python :: 3
Classifier: Operating System :: OS Independent
Requires-Python: >=3.9
License-File: LICENSE
Requires-Dist: numpy
Requires-Dist: scipy
Requires-Dist: casadi
Requires-Dist: ndsplines>=0.2.0post0
Provides-Extra: examples
Requires-Dist: matplotlib; extra == "examples"
Dynamic: license-file
